pytinyrenderer.pypy39-pp73-x86_64-linux-gnu.so
pytinyrenderer-0.0.14.dist-info/WHEEL
pytinyrenderer-0.0.14.dist-info/METADATA
pytinyrenderer-0.0.14.dist-info/top_level.txt
pytinyrenderer-0.0.14.dist-info/RECORD
pytinyrenderer-0.0.14.dist-info/LICENSE
