Metadata-Version: 2.1
Name: pytinyrenderer
Version: 0.0.14
Summary: Python bindings for Tiny Renderer
Home-page: https://github.com/erwincoumans/tinyrenderer
Author: Dmitry V. Sokolov, Erwin Coumans
Author-email: erwincoumans@google.com
License: Zlib/PNG License
Keywords: cpu,rendering,3d
Platform: any
Classifier: Development Status :: 5 - Production/Stable
Classifier: License :: OSI Approved :: zlib/libpng License
Classifier: Operating System :: Microsoft :: Windows
Classifier: Operating System :: POSIX :: Linux
Classifier: Operating System :: MacOS
Classifier: Intended Audience :: Science/Research
Classifier: Programming Language :: Python
Classifier: Programming Language :: Python :: 2.7
Classifier: Programming Language :: Python :: 3.4
Classifier: Programming Language :: Python :: 3.5
Classifier: Programming Language :: Python :: 3.6
Classifier: Programming Language :: Python :: 3.7
Classifier: Programming Language :: Python :: 3.8
Classifier: Topic :: Games/Entertainment :: Simulation
Classifier: Topic :: Scientific/Engineering :: Artificial Intelligence
Classifier: Framework :: Robot Framework
License-File: LICENSE
